README_PYPI.md
pyproject.toml
requirements-dev.txt
requirements.txt
bin/apiReqClient.py
bin/apiReqKerb.py
examples/downloadTwiki.py
examples/fastapi_server.py
examples/flask_server.py
examples/uploadTwiki.py
tests/conftest.py
tests/pytest.ini
tests/test_auth.py
tests/test_authfile.py
tests/test_authuser_kerb.py
tests/test_fastapi.py
tests/test_flask.py
tests/test_refresh.py
tests/test_tokenalgos.py
tsgauth/__init__.py
tsgauth/flaskoidc.py
tsgauth/oidcauth.py
tsgauth/fastapi/__init__.py
tsgauth/fastapi/authstores.py
tsgauth/fastapi/exceptions.py
tsgauth/fastapi/routes.py
tsgauth/fastapi/settings.py
tsgauth/fastapi/tokenutil.py
tsgauth-0.11.0.dist-info/METADATA
tsgauth-0.11.0.dist-info/WHEEL
tsgauth-0.11.0.dist-info/licenses/LICENSE.txt
tsgauth-0.11.0.dist-info/RECORD
