Metadata-Version: 2.4
Name: tsgauth
Version: 0.11.0
Summary: The TSG authentication library for use with the CERN SSO (OIDC based) service
Project-URL: Homepage, https://gitlab.cern.ch/cms-tsg/common/tsgauth
Project-URL: Bug Tracker, https://gitlab.cern.ch/cms-tsg/common/tsgauth/issues
Author-email: Sam Harper <cmstsg@cern.ch>
License-File: LICENSE.txt
Classifier: License :: OSI Approved :: MIT License
Classifier: Operating System :: OS Independent
Classifier: Programming Language :: Python :: 3
Requires-Python: >=3.9
Requires-Dist: authlib>=0.15
Requires-Dist: requests
Provides-Extra: dev
Requires-Dist: httpx; extra == 'dev'
Requires-Dist: pytest; extra == 'dev'
Provides-Extra: fastapi
Requires-Dist: aiocache; extra == 'fastapi'
Requires-Dist: fastapi[standard]; extra == 'fastapi'
Requires-Dist: itsdangerous; extra == 'fastapi'
Requires-Dist: pydantic-settings; extra == 'fastapi'
Requires-Dist: redis; extra == 'fastapi'
Provides-Extra: flask
Requires-Dist: flask>=2.0; extra == 'flask'
Requires-Dist: redis; extra == 'flask'
Provides-Extra: kerb
Requires-Dist: bs4; extra == 'kerb'
Requires-Dist: inputimeout; extra == 'kerb'
Requires-Dist: requests-gssapi; extra == 'kerb'
